freedesktop_os_release.py
freedesktop_os_release-0.0.0.dist-info/LICENSE
freedesktop_os_release-0.0.0.dist-info/WHEEL
freedesktop_os_release-0.0.0.dist-info/METADATA
freedesktop_os_release-0.0.0.dist-info/RECORD
